{
  "date": "2025-08-05",
  "timestamp": "2025-08-05T09:22:23.427Z",
  "rundown": "<b>Record:</b> 4-4 (0.500)  \n<b>Series:</b> Lost series to Kansas City Royals (1-2), Won series against Cincinnati Reds (3-1), Lost game to Milwaukee Brewers (0-1)  \n<b>Highlights:</b> High-scoring win 10-7 against the Kansas City Royals, thrilling 12-11 victory over the Cincinnati Reds, and Eli White's impressive week with 4 home runs and 11 RBIs.  \n<b>Trend:</b> Building momentum with recent solid play, especially highlighted by the offensive explosion against the Reds.",
  "weeklyStats": {
    "dateRange": "2025-07-28 to 2025-08-04",
    "record": "4-4",
    "wins": 4,
    "losses": 4,
    "winPct": "0.500",
    "totalGames": 8,
    "momentum": "building momentum with recent solid play",
    "topPitchers": [
      {
        "name": "Joey Wentz",
        "appearances": 8,
        "inningsPitched": 6.2,
        "earnedRuns": 0,
        "strikeouts": 7,
        "hits": 1,
        "wins": 0,
        "losses": 0,
        "saves": 0,
        "era": "0.00"
      },
      {
        "name": "Raisel Iglesias",
        "appearances": 8,
        "inningsPitched": 5,
        "earnedRuns": 0,
        "strikeouts": 4,
        "hits": 4,
        "wins": 0,
        "losses": 0,
        "saves": 4,
        "era": "0.00"
      },
      {
        "name": "Pierce Johnson",
        "appearances": 8,
        "inningsPitched": 2.6000000000000005,
        "earnedRuns": 0,
        "strikeouts": 2,
        "hits": 2,
        "wins": 1,
        "losses": 0,
        "saves": 0,
        "era": "0.00"
      }
    ],
    "topBatters": [
      {
        "name": "Eli White",
        "games": 7,
        "hits": 8,
        "homeRuns": 4,
        "rbi": 11,
        "runs": 6,
        "atBats": 27,
        "avg": "0.296"
      },
      {
        "name": "Austin Riley",
        "games": 7,
        "hits": 4,
        "homeRuns": 2,
        "rbi": 6,
        "runs": 3,
        "atBats": 27,
        "avg": "0.148"
      },
      {
        "name": "Marcell Ozuna",
        "games": 5,
        "hits": 4,
        "homeRuns": 2,
        "rbi": 6,
        "runs": 6,
        "atBats": 16,
        "avg": "0.250"
      },
      {
        "name": "Michael Harris II",
        "games": 8,
        "hits": 12,
        "homeRuns": 0,
        "rbi": 1,
        "runs": 5,
        "atBats": 34,
        "avg": "0.353"
      }
    ],
    "gameResults": [
      {
        "date": "7/28/2025",
        "result": "W",
        "score": "10-7",
        "opponent": "Kansas City Royals",
        "homeAway": "@"
      },
      {
        "date": "7/29/2025",
        "result": "L",
        "score": "6-9",
        "opponent": "Kansas City Royals",
        "homeAway": "@"
      },
      {
        "date": "7/30/2025",
        "result": "L",
        "score": "0-1",
        "opponent": "Kansas City Royals",
        "homeAway": "@"
      },
      {
        "date": "7/31/2025",
        "result": "W",
        "score": "12-11",
        "opponent": "Cincinnati Reds",
        "homeAway": "@"
      },
      {
        "date": "8/1/2025",
        "result": "L",
        "score": "2-3",
        "opponent": "Cincinnati Reds",
        "homeAway": "@"
      },
      {
        "date": "8/2/2025",
        "result": "W",
        "score": "4-2",
        "opponent": "Cincinnati Reds",
        "homeAway": "@"
      },
      {
        "date": "8/3/2025",
        "result": "W",
        "score": "4-2",
        "opponent": "Cincinnati Reds",
        "homeAway": "@"
      },
      {
        "date": "8/4/2025",
        "result": "L",
        "score": "1-3",
        "opponent": "Milwaukee Brewers",
        "homeAway": "vs"
      }
    ],
    "seriesResults": [
      {
        "opponent": "Kansas City Royals",
        "homeAway": "@",
        "record": "1-2",
        "outcome": "lost series",
        "games": [
          {
            "date": "7/28/2025",
            "result": "W",
            "score": "10-7"
          },
          {
            "date": "7/29/2025",
            "result": "L",
            "score": "6-9"
          },
          {
            "date": "7/30/2025",
            "result": "L",
            "score": "0-1"
          }
        ]
      },
      {
        "opponent": "Cincinnati Reds",
        "homeAway": "@",
        "record": "3-1",
        "outcome": "won series",
        "games": [
          {
            "date": "7/31/2025",
            "result": "W",
            "score": "12-11"
          },
          {
            "date": "8/1/2025",
            "result": "L",
            "score": "2-3"
          },
          {
            "date": "8/2/2025",
            "result": "W",
            "score": "4-2"
          },
          {
            "date": "8/3/2025",
            "result": "W",
            "score": "4-2"
          }
        ]
      },
      {
        "opponent": "Milwaukee Brewers",
        "homeAway": "vs",
        "record": "0-1",
        "outcome": "lost game",
        "games": [
          {
            "date": "8/4/2025",
            "result": "L",
            "score": "1-3"
          }
        ]
      }
    ],
    "highlights": [
      "High-scoring W 10-7 @ Kansas City Royals",
      "High-scoring L 6-9 @ Kansas City Royals",
      "High-scoring W 12-11 @ Cincinnati Reds",
      "Close L 0-1 @ Kansas City Royals",
      "Close W 12-11 @ Cincinnati Reds",
      "Close L 2-3 @ Cincinnati Reds"
    ]
  }
}